medimtools/__init__.py
medimtools/cli.py
medimtools/convert/__init__.py
medimtools/convert/ops.py
medimtools/stats/__init__.py
medimtools/stats/label.py
medimtools/viz/__init__.py
medimtools/viz/ops.py
medimtools/viz/sitk.py
medimtools-0.1.20.dist-info/AUTHORS.rst
medimtools-0.1.20.dist-info/LICENSE
medimtools-0.1.20.dist-info/METADATA
medimtools-0.1.20.dist-info/WHEEL
medimtools-0.1.20.dist-info/entry_points.txt
medimtools-0.1.20.dist-info/top_level.txt
medimtools-0.1.20.dist-info/RECORD
