Metadata-Version: 2.1
Name: medimtools
Version: 0.1.20
Summary: Python Boilerplate contains all the boilerplate you need to create a Python package.
Home-page: https://github.com/surajpaib/medimtools
Author: Suraj Pai
Author-email: b.pai@maastrichtuniversity.nl
License: MIT license
Keywords: medimtools
Classifier: Development Status :: 2 - Pre-Alpha
Classifier: Intended Audience :: Developers
Classifier: License :: OSI Approved :: MIT License
Classifier: Natural Language :: English
Classifier: Programming Language :: Python :: 3
Classifier: Programming Language :: Python :: 3.6
Classifier: Programming Language :: Python :: 3.7
Classifier: Programming Language :: Python :: 3.8
Requires-Python: >=3.6
License-File: LICENSE
License-File: AUTHORS.rst
Requires-Dist: Click (>7)
